logicpuzzletools/__init__.py
logicpuzzletools/logic_puzzle_tools.py
logicpuzzletools/logic_puzzles.py
logicpuzzletools-0.1.0.dist-info/LICENSE.txt
logicpuzzletools-0.1.0.dist-info/METADATA
logicpuzzletools-0.1.0.dist-info/WHEEL
logicpuzzletools-0.1.0.dist-info/top_level.txt
logicpuzzletools-0.1.0.dist-info/RECORD
