Metadata-Version: 2.1
Name: logicpuzzletools
Version: 0.1.0
Summary: A collection of tools to aid in solving logic grid puzzles
Home-page: https://github.com/DanLBates/LogicPuzzleTools
Author: Daniel L. Bates
Author-email: danbates@verizon.net
License: UNKNOWN
Keywords: 'Logic','Grid','Puzzle','Problem','Tool'
Platform: UNKNOWN
Classifier: Programming Language :: Python :: 3
Classifier: License :: OSI Approved :: MIT License
Classifier: Operating System :: OS Independent
Classifier: Intended Audience :: End Users/Desktop
Requires-Python: >=3.6
License-File: LICENSE.txt
